{"head":{"link":[],"vars":["s","p","o"]},"results":{"distinct":false,"ordered":true,"bindings":[{"s":{"type":"uri","value":"http://dbpedia.org/resource/Microsoft_HoloLens"},"p":{"type":"uri","value":"http://dbpedia.org/ontology/wikiPageID"},"o":{"type":"literal","value":45153914,"datatype":"http://www.w3.org/2001/XMLSchema#integer"}},{"s":{"type":"uri","value":"http://dbpedia.org/resource/Microsoft_HoloLens"},"p":{"type":"uri","value":"http://dbpedia.org/ontology/wikiPageRedirects"},"o":{"type":"uri","value":"http://dbpedia.org/resource/Windows_Holographic"}},{"s":{"type":"uri","value":"http://dbpedia.org/resource/Microsoft_HoloLens"},"p":{"type":"uri","value":"http://www.w3.org/2000/01/rdf-schema#label"},"o":{"type":"literal","value":"Microsoft HoloLens","lang":"en"}},{"s":{"type":"uri","value":"http://dbpedia.org/resource/Microsoft_HoloLens"},"p":{"type":"uri","value":"http://xmlns.com/foaf/0.1/isPrimaryTopicOf"},"o":{"type":"uri","value":"http://en.wikipedia.org/wiki/Microsoft_HoloLens"}},{"s":{"type":"uri","value":"http://dbpedia.org/resource/Microsoft_HoloLens"},"p":{"type":"uri","value":"http://www.w3.org/ns/prov#wasDerivedFrom"},"o":{"type":"uri","value":"http://en.wikipedia.org/wiki/Microsoft_HoloLens?oldid=682210127"}},{"s":{"type":"uri","value":"http://dbpedia.org/resource/Microsoft_HoloLens"},"p":{"type":"uri","value":"http://dbpedia.org/ontology/wikiPageRevisionID"},"o":{"type":"literal","value":682210127,"datatype":"http://www.w3.org/2001/XMLSchema#integer"}},{"s":{"type":"uri","value":"http://en.wikipedia.org/wiki/Microsoft_HoloLens"},"p":{"type":"uri","value":"http://xmlns.com/foaf/0.1/primaryTopic"},"o":{"type":"uri","value":"http://dbpedia.org/resource/Microsoft_HoloLens"}}]}}