{"head":{"link":[],"vars":["s","p","o"]},"results":{"distinct":false,"ordered":true,"bindings":[{"s":{"type":"uri","value":"http://dbpedia.org/resource/Sculpteo"},"p":{"type":"uri","value":"http://dbpedia.org/ontology/wikiPageWikiLink"},"o":{"type":"uri","value":"http://dbpedia.org/resource/IPhone_5"}},{"s":{"type":"uri","value":"http://dbpedia.org/resource/Sculpteo"},"p":{"type":"uri","value":"http://dbpedia.org/ontology/wikiPageWikiLink"},"o":{"type":"uri","value":"http://dbpedia.org/resource/IOS"}},{"s":{"type":"uri","value":"http://dbpedia.org/resource/Sculpteo"},"p":{"type":"uri","value":"http://www.w3.org/1999/02/22-rdf-syntax-ns#type"},"o":{"type":"uri","value":"http://dbpedia.org/class/yago/YagoPermanentlyLocatedEntity"}},{"s":{"type":"uri","value":"http://dbpedia.org/resource/Sculpteo"},"p":{"type":"uri","value":"http://dbpedia.org/ontology/wikiPageWikiLink"},"o":{"type":"uri","value":"http://dbpedia.org/resource/Adobe_Creative_Cloud"}},{"s":{"type":"uri","value":"http://dbpedia.org/resource/Sculpteo"},"p":{"type":"uri","value":"http://www.w3.org/2002/07/owl#sameAs"},"o":{"type":"uri","value":"http://www.wikidata.org/entity/Q7439439"}},{"s":{"type":"uri","value":"http://dbpedia.org/resource/Sculpteo"},"p":{"type":"uri","value":"http://www.w3.org/1999/02/22-rdf-syntax-ns#type"},"o":{"type":"uri","value":"http://dbpedia.org/class/yago/YagoLegalActor"}},{"s":{"type":"uri","value":"http://dbpedia.org/resource/Sculpteo"},"p":{"type":"uri","value":"http://www.w3.org/1999/02/22-rdf-syntax-ns#type"},"o":{"type":"uri","value":"http://dbpedia.org/class/yago/YagoLegalActorGeo"}},{"s":{"type":"uri","value":"http://dbpedia.org/resource/Sculpteo"},"p":{"type":"uri","value":"http://dbpedia.org/ontology/wikiPageWikiLink"},"o":{"type":"uri","value":"http://dbpedia.org/resource/Category:2009_establishments_in_France"}},{"s":{"type":"uri","value":"http://dbpedia.org/resource/Materialise_NV"},"p":{"type":"uri","value":"http://dbpedia.org/ontology/wikiPageWikiLink"},"o":{"type":"uri","value":"http://dbpedia.org/resource/Sculpteo"}},{"s":{"type":"uri","value":"http://dbpedia.org/resource/Sculpteo"},"p":{"type":"uri","value":"http://dbpedia.org/ontology/wikiPageWikiLink"},"o":{"type":"uri","value":"http://dbpedia.org/resource/La_Poste_(France)"}},{"s":{"type":"uri","value":"http://dbpedia.org/resource/Sculpteo"},"p":{"type":"uri","value":"http://xmlns.com/foaf/0.1/isPrimaryTopicOf"},"o":{"type":"uri","value":"http://en.wikipedia.org/wiki/Sculpteo"}},{"s":{"type":"uri","value":"http://dbpedia.org/resource/Sculpteo"},"p":{"type":"uri","value":"http://www.w3.org/2000/01/rdf-schema#comment"},"o":{"type":"literal","value":"Sculpteo is a French company specialized in 3D printing in the cloud. Sculpteo offers an online 3D printing service, using rapid prototyping and a manufacturing process  involving laser sintering or stereo lithography. The company was founded in June 2009 by Eric Carreel (co-founder of Inventel, acquired by Technicolor in 2005, and Withings), Clement Moreau  and Jacques Lewiner. Sculpteo offers online printing services, particularly in Europe and North America","lang":"en"}},{"s":{"type":"uri","value":"http://dbpedia.org/resource/Sculpteo"},"p":{"type":"uri","value":"http://dbpedia.org/ontology/wikiPageWikiLink"},"o":{"type":"uri","value":"http://dbpedia.org/resource/Materialise_NV"}},{"s":{"type":"uri","value":"http://dbpedia.org/resource/Sculpteo"},"p":{"type":"uri","value":"http://purl.org/dc/terms/subject"},"o":{"type":"uri","value":"http://dbpedia.org/resource/Category:2009_establishments_in_France"}},{"s":{"type":"uri","value":"http://dbpedia.org/resource/Sculpteo"},"p":{"type":"uri","value":"http://dbpedia.org/ontology/wikiPageExternalLink"},"o":{"type":"uri","value":"http://www.sculpteo.com/"}},{"s":{"type":"uri","value":"http://dbpedia.org/resource/Sculpteo"},"p":{"type":"uri","value":"http://dbpedia.org/ontology/wikiPageWikiLink"},"o":{"type":"uri","value":"http://dbpedia.org/resource/IPhone"}},{"s":{"type":"uri","value":"http://dbpedia.org/resource/Sculpteo"},"p":{"type":"uri","value":"http://purl.org/linguistics/gold/hypernym"},"o":{"type":"uri","value":"http://dbpedia.org/resource/Company"}},{"s":{"type":"uri","value":"http://dbpedia.org/resource/Sculpteo"},"p":{"type":"uri","value":"http://dbpedia.org/ontology/wikiPageWikiLink"},"o":{"type":"uri","value":"http://dbpedia.org/resource/Kraftwurx"}},{"s":{"type":"uri","value":"http://dbpedia.org/resource/Sculpteo"},"p":{"type":"uri","value":"http://dbpedia.org/ontology/wikiPageWikiLink"},"o":{"type":"uri","value":"http://dbpedia.org/resource/Consumer_Electronics_Show"}},{"s":{"type":"uri","value":"http://dbpedia.org/resource/Sculpteo"},"p":{"type":"uri","value":"http://dbpedia.org/ontology/wikiPageWikiLink"},"o":{"type":"uri","value":"http://dbpedia.org/resource/Laser"}},{"s":{"type":"uri","value":"http://dbpedia.org/resource/Sculpteo"},"p":{"type":"uri","value":"http://www.w3.org/2002/07/owl#sameAs"},"o":{"type":"uri","value":"http://fr.dbpedia.org/resource/Sculpteo"}},{"s":{"type":"uri","value":"http://dbpedia.org/resource/Sculpteo"},"p":{"type":"uri","value":"http://dbpedia.org/ontology/wikiPageWikiLink"},"o":{"type":"uri","value":"http://dbpedia.org/resource/France"}},{"s":{"type":"uri","value":"http://dbpedia.org/resource/Sculpteo"},"p":{"type":"uri","value":"http://dbpedia.org/ontology/wikiPageWikiLink"},"o":{"type":"uri","value":"http://dbpedia.org/resource/Continuous_Liquid_Interface_Production"}},{"s":{"type":"uri","value":"http://dbpedia.org/resource/Sculpteo"},"p":{"type":"uri","value":"http://www.w3.org/1999/02/22-rdf-syntax-ns#type"},"o":{"type":"uri","value":"http://dbpedia.org/ontology/Agent"}},{"s":{"type":"uri","value":"http://dbpedia.org/resource/Sculpteo"},"p":{"type":"uri","value":"http://dbpedia.org/ontology/wikiPageWikiLink"},"o":{"type":"uri","value":"http://dbpedia.org/resource/Technicolor"}},{"s":{"type":"uri","value":"http://dbpedia.org/resource/Sculpteo"},"p":{"type":"uri","value":"http://dbpedia.org/ontology/wikiPageWikiLink"},"o":{"type":"uri","value":"http://dbpedia.org/resource/3D_Printing_Marketplace"}},{"s":{"type":"uri","value":"http://dbpedia.org/resource/Sculpteo"},"p":{"type":"uri","value":"http://www.w3.org/1999/02/22-rdf-syntax-ns#type"},"o":{"type":"uri","value":"http://www.wikidata.org/entity/Q43229"}},{"s":{"type":"uri","value":"http://dbpedia.org/resource/Sculpteo"},"p":{"type":"uri","value":"http://dbpedia.org/ontology/wikiPageWikiLink"},"o":{"type":"uri","value":"http://dbpedia.org/resource/Pinshape"}},{"s":{"type":"uri","value":"http://dbpedia.org/resource/Sculpteo"},"p":{"type":"uri","value":"http://www.w3.org/1999/02/22-rdf-syntax-ns#type"},"o":{"type":"uri","value":"http://dbpedia.org/ontology/Company"}},{"s":{"type":"uri","value":"http://dbpedia.org/resource/Invoxia"},"p":{"type":"uri","value":"http://dbpedia.org/ontology/wikiPageWikiLink"},"o":{"type":"uri","value":"http://dbpedia.org/resource/Sculpteo"}},{"s":{"type":"uri","value":"http://dbpedia.org/resource/Sculpteo"},"p":{"type":"uri","value":"http://dbpedia.org/ontology/wikiPageWikiLink"},"o":{"type":"uri","value":"http://dbpedia.org/resource/3DVIA"}},{"s":{"type":"uri","value":"http://dbpedia.org/resource/Sculpteo"},"p":{"type":"uri","value":"http://dbpedia.org/ontology/wikiPageID"},"o":{"type":"literal","value":35194697,"datatype":"http://www.w3.org/2001/XMLSchema#integer"}},{"s":{"type":"uri","value":"http://dbpedia.org/resource/Sculpteo"},"p":{"type":"uri","value":"http://dbpedia.org/ontology/wikiPageWikiLink"},"o":{"type":"uri","value":"http://dbpedia.org/resource/Stereo_lithography"}},{"s":{"type":"uri","value":"http://dbpedia.org/resource/Sculpteo"},"p":{"type":"uri","value":"http://dbpedia.org/ontology/wikiPageWikiLink"},"o":{"type":"uri","value":"http://dbpedia.org/resource/L'Usine_nouvelle"}},{"s":{"type":"uri","value":"http://dbpedia.org/resource/Sculpteo"},"p":{"type":"uri","value":"http://xmlns.com/foaf/0.1/depiction"},"o":{"type":"uri","value":"http://commons.wikimedia.org/wiki/Special:FilePath/Logo_sculpteo.jpg"}},{"s":{"type":"uri","value":"http://dbpedia.org/resource/3D_printing_marketplace"},"p":{"type":"uri","value":"http://dbpedia.org/ontology/wikiPageWikiLink"},"o":{"type":"uri","value":"http://dbpedia.org/resource/Sculpteo"}},{"s":{"type":"uri","value":"http://dbpedia.org/resource/Jacques_Lewiner"},"p":{"type":"uri","value":"http://dbpedia.org/ontology/wikiPageWikiLink"},"o":{"type":"uri","value":"http://dbpedia.org/resource/Sculpteo"}},{"s":{"type":"uri","value":"http://dbpedia.org/resource/Sculpteo"},"p":{"type":"uri","value":"http://dbpedia.org/ontology/wikiPageWikiLink"},"o":{"type":"uri","value":"http://dbpedia.org/resource/Eric_Carreel"}},{"s":{"type":"uri","value":"http://dbpedia.org/resource/Sculpteo"},"p":{"type":"uri","value":"http://dbpedia.org/ontology/wikiPageWikiLink"},"o":{"type":"uri","value":"http://dbpedia.org/resource/Sintering"}},{"s":{"type":"uri","value":"http://dbpedia.org/resource/Sculpteo"},"p":{"type":"uri","value":"http://dbpedia.org/ontology/wikiPageWikiLink"},"o":{"type":"uri","value":"http://dbpedia.org/resource/Amazon.com"}},{"s":{"type":"uri","value":"http://dbpedia.org/resource/Sculpteo"},"p":{"type":"uri","value":"http://www.w3.org/2000/01/rdf-schema#label"},"o":{"type":"literal","value":"Sculpteo","lang":"fr"}},{"s":{"type":"uri","value":"http://dbpedia.org/resource/Sculpteo"},"p":{"type":"uri","value":"http://www.w3.org/2002/07/owl#sameAs"},"o":{"type":"uri","value":"http://wikidata.dbpedia.org/resource/Q7439439"}},{"s":{"type":"uri","value":"http://dbpedia.org/resource/Sculpteo"},"p":{"type":"uri","value":"http://dbpedia.org/ontology/wikiPageWikiLink"},"o":{"type":"uri","value":"http://dbpedia.org/resource/3DLT"}},{"s":{"type":"uri","value":"http://dbpedia.org/resource/Sculpteo"},"p":{"type":"uri","value":"http://www.w3.org/1999/02/22-rdf-syntax-ns#type"},"o":{"type":"uri","value":"http://dbpedia.org/ontology/Organisation"}},{"s":{"type":"uri","value":"http://dbpedia.org/resource/Sculpteo"},"p":{"type":"uri","value":"http://dbpedia.org/ontology/wikiPageRevisionID"},"o":{"type":"literal","value":745320648,"datatype":"http://www.w3.org/2001/XMLSchema#integer"}},{"s":{"type":"uri","value":"http://dbpedia.org/resource/Sculpteo"},"p":{"type":"uri","value":"http://dbpedia.org/ontology/abstract"},"o":{"type":"literal","value":"Sculpteo is a French company specialized in 3D printing in the cloud. Sculpteo offers an online 3D printing service, using rapid prototyping and a manufacturing process  involving laser sintering or stereo lithography. The company was founded in June 2009 by Eric Carreel (co-founder of Inventel, acquired by Technicolor in 2005, and Withings), Clement Moreau  and Jacques Lewiner. Sculpteo offers online printing services, particularly in Europe and North America","lang":"en"}},{"s":{"type":"uri","value":"http://dbpedia.org/resource/Sculpteo"},"p":{"type":"uri","value":"http://dbpedia.org/ontology/wikiPageWikiLink"},"o":{"type":"uri","value":"http://dbpedia.org/resource/3dvia"}},{"s":{"type":"uri","value":"http://dbpedia.org/resource/Shapeways"},"p":{"type":"uri","value":"http://dbpedia.org/ontology/wikiPageWikiLink"},"o":{"type":"uri","value":"http://dbpedia.org/resource/Sculpteo"}},{"s":{"type":"uri","value":"http://dbpedia.org/resource/Sculpteo"},"p":{"type":"uri","value":"http://www.w3.org/1999/02/22-rdf-syntax-ns#type"},"o":{"type":"uri","value":"http://dbpedia.org/class/yago/Institution108053576"}},{"s":{"type":"uri","value":"http://dbpedia.org/resource/Sculpteo"},"p":{"type":"uri","value":"http://dbpedia.org/ontology/type"},"o":{"type":"uri","value":"http://dbpedia.org/resource/Privately_held_company"}},{"s":{"type":"uri","value":"http://dbpedia.org/resource/Sculpteo"},"p":{"type":"uri","value":"http://dbpedia.org/ontology/wikiPageWikiLink"},"o":{"type":"uri","value":"http://dbpedia.org/resource/Xange"}},{"s":{"type":"uri","value":"http://dbpedia.org/resource/Sculpteo"},"p":{"type":"uri","value":"http://www.w3.org/1999/02/22-rdf-syntax-ns#type"},"o":{"type":"uri","value":"http://dbpedia.org/class/yago/WikicatCompaniesOfFrance"}},{"s":{"type":"uri","value":"http://dbpedia.org/resource/Sculpteo"},"p":{"type":"uri","value":"http://www.w3.org/1999/02/22-rdf-syntax-ns#type"},"o":{"type":"uri","value":"http://www.w3.org/2002/07/owl#Thing"}},{"s":{"type":"uri","value":"http://dbpedia.org/resource/3DLT"},"p":{"type":"uri","value":"http://dbpedia.org/ontology/wikiPageWikiLink"},"o":{"type":"uri","value":"http://dbpedia.org/resource/Sculpteo"}},{"s":{"type":"uri","value":"http://dbpedia.org/resource/Sculpteo"},"p":{"type":"uri","value":"http://www.w3.org/1999/02/22-rdf-syntax-ns#type"},"o":{"type":"uri","value":"http://dbpedia.org/class/yago/Company108058098"}},{"s":{"type":"uri","value":"http://dbpedia.org/resource/Sculpteo"},"p":{"type":"uri","value":"http://dbpedia.org/ontology/wikiPageWikiLink"},"o":{"type":"uri","value":"http://dbpedia.org/resource/3D_printing"}},{"s":{"type":"uri","value":"http://dbpedia.org/resource/Sculpteo"},"p":{"type":"uri","value":"http://www.w3.org/1999/02/22-rdf-syntax-ns#type"},"o":{"type":"uri","value":"http://www.wikidata.org/entity/Q24229398"}},{"s":{"type":"uri","value":"http://dbpedia.org/resource/Sculpteo"},"p":{"type":"uri","value":"http://dbpedia.org/ontology/abstract"},"o":{"type":"literal","value":"Sculpteo est une société française spécialisée dans l’impression 3D. Sculpteo propose un service d'impression 3D en ligne, prototypage rapide utilisant les procédés de fabrication tels que le frittage laser ou la stéréolithographie. Elle a été fondée en juin 2009 par Eric Carreel cofondateur d’Inventel, cédé à Technicolor en 2005 et de Withings, Clément Moreau et Jacques Lewiner. Sculpteo propose son service d'impression en ligne notamment en Europe et en Amérique du Nord.","lang":"fr"}},{"s":{"type":"uri","value":"http://dbpedia.org/resource/Sculpteo"},"p":{"type":"uri","value":"http://dbpedia.org/property/logo"},"o":{"type":"literal","value":"Logo sculpteo.jpg","datatype":"http://www.w3.org/1999/02/22-rdf-syntax-ns#langString"}},{"s":{"type":"uri","value":"http://dbpedia.org/resource/Sculpteo"},"p":{"type":"uri","value":"http://dbpedia.org/property/founders"},"o":{"type":"literal","value":"Clément Moreau","datatype":"http://www.w3.org/1999/02/22-rdf-syntax-ns#langString"}},{"s":{"type":"uri","value":"http://dbpedia.org/resource/Sculpteo"},"p":{"type":"uri","value":"http://www.w3.org/2002/07/owl#sameAs"},"o":{"type":"uri","value":"http://rdf.freebase.com/ns/m.0h7pm4c"}},{"s":{"type":"uri","value":"http://dbpedia.org/resource/3D_publishing"},"p":{"type":"uri","value":"http://dbpedia.org/ontology/wikiPageWikiLink"},"o":{"type":"uri","value":"http://dbpedia.org/resource/Sculpteo"}},{"s":{"type":"uri","value":"http://dbpedia.org/resource/Sculpteo"},"p":{"type":"uri","value":"http://www.w3.org/1999/02/22-rdf-syntax-ns#type"},"o":{"type":"uri","value":"http://dbpedia.org/class/yago/SocialGroup107950920"}},{"s":{"type":"uri","value":"http://dbpedia.org/resource/Sculpteo"},"p":{"type":"uri","value":"http://dbpedia.org/ontology/wikiPageWikiLink"},"o":{"type":"uri","value":"http://dbpedia.org/resource/Observeur_du_Design"}},{"s":{"type":"uri","value":"http://dbpedia.org/resource/Sculpteo"},"p":{"type":"uri","value":"http://www.w3.org/2000/01/rdf-schema#label"},"o":{"type":"literal","value":"Sculpteo","lang":"en"}},{"s":{"type":"uri","value":"http://dbpedia.org/resource/Sculpteo"},"p":{"type":"uri","value":"http://www.w3.org/1999/02/22-rdf-syntax-ns#type"},"o":{"type":"uri","value":"http://schema.org/Organization"}},{"s":{"type":"uri","value":"http://dbpedia.org/resource/Sculpteo"},"p":{"type":"uri","value":"http://dbpedia.org/ontology/wikiPageWikiLink"},"o":{"type":"uri","value":"http://dbpedia.org/resource/Jacques_Lewiner"}},{"s":{"type":"uri","value":"http://dbpedia.org/resource/Sculpteo"},"p":{"type":"uri","value":"http://dbpedia.org/property/locationCountry"},"o":{"type":"literal","value":"France","datatype":"http://www.w3.org/1999/02/22-rdf-syntax-ns#langString"}},{"s":{"type":"uri","value":"http://dbpedia.org/resource/Sculpteo"},"p":{"type":"uri","value":"http://www.w3.org/1999/02/22-rdf-syntax-ns#type"},"o":{"type":"uri","value":"http://www.ontologydesignpatterns.org/ont/dul/DUL.owl#Agent"}},{"s":{"type":"uri","value":"http://dbpedia.org/resource/Sculpteo"},"p":{"type":"uri","value":"http://dbpedia.org/property/locationCity"},"o":{"type":"literal","value":"Villejuif","datatype":"http://www.w3.org/1999/02/22-rdf-syntax-ns#langString"}},{"s":{"type":"uri","value":"http://dbpedia.org/resource/Sculpteo"},"p":{"type":"uri","value":"http://www.w3.org/1999/02/22-rdf-syntax-ns#type"},"o":{"type":"uri","value":"http://dbpedia.org/class/yago/WikicatCompaniesEstablishedIn2009"}},{"s":{"type":"uri","value":"http://dbpedia.org/resource/Sculpteo"},"p":{"type":"uri","value":"http://dbpedia.org/property/founders"},"o":{"type":"uri","value":"http://dbpedia.org/resource/Eric_Carreel"}},{"s":{"type":"uri","value":"http://dbpedia.org/resource/Sculpteo"},"p":{"type":"uri","value":"http://www.w3.org/2000/01/rdf-schema#comment"},"o":{"type":"literal","value":"Sculpteo est une société française spécialisée dans l’impression 3D. Sculpteo propose un service d'impression 3D en ligne, prototypage rapide utilisant les procédés de fabrication tels que le frittage laser ou la stéréolithographie. Elle a été fondée en juin 2009 par Eric Carreel cofondateur d’Inventel, cédé à Technicolor en 2005 et de Withings, Clément Moreau et Jacques Lewiner. Sculpteo propose son service d'impression en ligne notamment en Europe et en Amérique du Nord.","lang":"fr"}},{"s":{"type":"uri","value":"http://dbpedia.org/resource/Sculpteo"},"p":{"type":"uri","value":"http://www.w3.org/2002/07/owl#sameAs"},"o":{"type":"uri","value":"http://yago-knowledge.org/resource/Sculpteo"}},{"s":{"type":"uri","value":"http://dbpedia.org/resource/Sculpteo"},"p":{"type":"uri","value":"http://dbpedia.org/ontology/thumbnail"},"o":{"type":"uri","value":"http://commons.wikimedia.org/wiki/Special:FilePath/Logo_sculpteo.jpg?width=300"}},{"s":{"type":"uri","value":"http://dbpedia.org/resource/Sculpteo"},"p":{"type":"uri","value":"http://dbpedia.org/ontology/wikiPageWikiLink"},"o":{"type":"uri","value":"http://dbpedia.org/resource/Inventel"}},{"s":{"type":"uri","value":"http://dbpedia.org/resource/Sculpteo"},"p":{"type":"uri","value":"http://dbpedia.org/ontology/wikiPageWikiLink"},"o":{"type":"uri","value":"http://dbpedia.org/resource/Sprout_(computer)"}},{"s":{"type":"uri","value":"http://en.wikipedia.org/wiki/Sculpteo"},"p":{"type":"uri","value":"http://xmlns.com/foaf/0.1/primaryTopic"},"o":{"type":"uri","value":"http://dbpedia.org/resource/Sculpteo"}},{"s":{"type":"uri","value":"http://dbpedia.org/resource/Sculpteo"},"p":{"type":"uri","value":"http://dbpedia.org/ontology/wikiPageWikiLink"},"o":{"type":"uri","value":"http://dbpedia.org/resource/Sketchfab"}},{"s":{"type":"uri","value":"http://dbpedia.org/resource/Sculpteo"},"p":{"type":"uri","value":"http://www.w3.org/1999/02/22-rdf-syntax-ns#type"},"o":{"type":"uri","value":"http://dbpedia.org/class/yago/Group100031264"}},{"s":{"type":"uri","value":"http://dbpedia.org/resource/Sculpteo"},"p":{"type":"uri","value":"http://www.w3.org/1999/02/22-rdf-syntax-ns#type"},"o":{"type":"uri","value":"http://www.ontologydesignpatterns.org/ont/dul/DUL.owl#SocialPerson"}},{"s":{"type":"uri","value":"http://dbpedia.org/resource/Sculpteo"},"p":{"type":"uri","value":"http://dbpedia.org/ontology/industry"},"o":{"type":"uri","value":"http://dbpedia.org/resource/3D_printing"}},{"s":{"type":"uri","value":"http://dbpedia.org/resource/Sculpteo"},"p":{"type":"uri","value":"http://dbpedia.org/ontology/wikiPageWikiLink"},"o":{"type":"uri","value":"http://dbpedia.org/resource/Thingiverse"}},{"s":{"type":"uri","value":"http://dbpedia.org/resource/Thingiverse"},"p":{"type":"uri","value":"http://dbpedia.org/ontology/wikiPageWikiLink"},"o":{"type":"uri","value":"http://dbpedia.org/resource/Sculpteo"}},{"s":{"type":"uri","value":"http://dbpedia.org/resource/Sculpteo"},"p":{"type":"uri","value":"http://dbpedia.org/property/founders"},"o":{"type":"uri","value":"http://dbpedia.org/resource/Jacques_Lewiner"}},{"s":{"type":"uri","value":"http://dbpedia.org/resource/Sculpteo"},"p":{"type":"uri","value":"http://purl.org/dc/terms/subject"},"o":{"type":"uri","value":"http://dbpedia.org/resource/Category:Online_companies"}},{"s":{"type":"uri","value":"http://dbpedia.org/resource/Sculpteo"},"p":{"type":"uri","value":"http://dbpedia.org/ontology/wikiPageWikiLink"},"o":{"type":"uri","value":"http://dbpedia.org/resource/Category:Companies_of_France"}},{"s":{"type":"uri","value":"http://dbpedia.org/resource/Printing"},"p":{"type":"uri","value":"http://dbpedia.org/ontology/wikiPageWikiLink"},"o":{"type":"uri","value":"http://dbpedia.org/resource/Sculpteo"}},{"s":{"type":"uri","value":"http://dbpedia.org/resource/Sculpteo"},"p":{"type":"uri","value":"http://www.w3.org/ns/prov#wasDerivedFrom"},"o":{"type":"uri","value":"http://en.wikipedia.org/wiki/Sculpteo?oldid=745320648"}},{"s":{"type":"uri","value":"http://dbpedia.org/resource/Sculpteo"},"p":{"type":"uri","value":"http://dbpedia.org/ontology/wikiPageWikiLink"},"o":{"type":"uri","value":"http://dbpedia.org/resource/Withings"}},{"s":{"type":"uri","value":"http://dbpedia.org/resource/Sculpteo"},"p":{"type":"uri","value":"http://purl.org/dc/terms/subject"},"o":{"type":"uri","value":"http://dbpedia.org/resource/Category:Companies_of_France"}},{"s":{"type":"uri","value":"http://dbpedia.org/resource/Sculpteo"},"p":{"type":"uri","value":"http://www.w3.org/1999/02/22-rdf-syntax-ns#type"},"o":{"type":"uri","value":"http://dbpedia.org/class/yago/Organization108008335"}},{"s":{"type":"uri","value":"http://dbpedia.org/resource/Sculpteo"},"p":{"type":"uri","value":"http://dbpedia.org/ontology/wikiPageWikiLink"},"o":{"type":"uri","value":"http://dbpedia.org/resource/Rapid_prototyping"}},{"s":{"type":"uri","value":"http://dbpedia.org/resource/Sculpteo"},"p":{"type":"uri","value":"http://dbpedia.org/ontology/wikiPageWikiLink"},"o":{"type":"uri","value":"http://dbpedia.org/resource/La_Banque_postale"}},{"s":{"type":"uri","value":"http://dbpedia.org/resource/Sculpteo"},"p":{"type":"uri","value":"http://www.w3.org/1999/02/22-rdf-syntax-ns#type"},"o":{"type":"uri","value":"http://dbpedia.org/class/yago/Abstraction100002137"}},{"s":{"type":"uri","value":"http://dbpedia.org/resource/Sculpteo"},"p":{"type":"uri","value":"http://dbpedia.org/ontology/wikiPageWikiLink"},"o":{"type":"uri","value":"http://dbpedia.org/resource/Category:Online_companies"}},{"s":{"type":"uri","value":"http://dbpedia.org/resource/Éric_Carreel"},"p":{"type":"uri","value":"http://dbpedia.org/ontology/wikiPageWikiLink"},"o":{"type":"uri","value":"http://dbpedia.org/resource/Sculpteo"}},{"s":{"type":"uri","value":"http://dbpedia.org/resource/Sculpteo"},"p":{"type":"uri","value":"http://dbpedia.org/ontology/wikiPageWikiLink"},"o":{"type":"uri","value":"http://dbpedia.org/resource/Category:3D_printing_websites"}},{"s":{"type":"uri","value":"http://dbpedia.org/resource/Sculpteo"},"p":{"type":"uri","value":"http://xmlns.com/foaf/0.1/homepage"},"o":{"type":"uri","value":"http://www.sculpteo.com/"}},{"s":{"type":"uri","value":"http://dbpedia.org/resource/Sculpteo"},"p":{"type":"uri","value":"http://purl.org/dc/terms/subject"},"o":{"type":"uri","value":"http://dbpedia.org/resource/Category:3D_printing_websites"}},{"s":{"type":"uri","value":"http://dbpedia.org/resource/Sculpteo"},"p":{"type":"uri","value":"http://dbpedia.org/ontology/wikiPageWikiLink"},"o":{"type":"uri","value":"http://dbpedia.org/resource/Shapeways"}},{"s":{"type":"uri","value":"http://dbpedia.org/resource/Sculpteo"},"p":{"type":"uri","value":"http://dbpedia.org/ontology/wikiPageWikiLink"},"o":{"type":"uri","value":"http://dbpedia.org/resource/Privately_held_company"}}]}}