{"head":{"link":[],"vars":["s","p","o"]},"results":{"distinct":false,"ordered":true,"bindings":[{"s":{"type":"uri","value":"http://dbpedia.org/resource/Feedly"},"p":{"type":"uri","value":"http://www.w3.org/2002/07/owl#sameAs"},"o":{"type":"uri","value":"http://nl.dbpedia.org/resource/Feedly"}},{"s":{"type":"uri","value":"http://dbpedia.org/resource/Feedly"},"p":{"type":"uri","value":"http://www.w3.org/2000/01/rdf-schema#comment"},"o":{"type":"literal","value":"Feedly — новостной агрегатор, представленный как альтернатива закрывшемуся Google Reader.","lang":"ru"}},{"s":{"type":"uri","value":"http://dbpedia.org/resource/Feedly"},"p":{"type":"uri","value":"http://www.w3.org/2002/07/owl#sameAs"},"o":{"type":"uri","value":"http://rdf.freebase.com/ns/m.0gj66tc"}},{"s":{"type":"uri","value":"http://dbpedia.org/resource/Feedly"},"p":{"type":"uri","value":"http://purl.org/dc/terms/subject"},"o":{"type":"uri","value":"http://dbpedia.org/resource/Category:News_aggregators"}},{"s":{"type":"uri","value":"http://dbpedia.org/resource/Feedly"},"p":{"type":"uri","value":"http://www.w3.org/2000/01/rdf-schema#comment"},"o":{"type":"literal","value":"Feedly是一个RSS聚合器应用程序，支持各种网页浏览器和运行iOS或Android的移动设备，也是一个基于云端的服务。其从各种在线资源聚合用户自定的新闻订阅源，并可与他人分享。Feedly由DevHD于2008年推出。","lang":"zh"}},{"s":{"type":"uri","value":"http://dbpedia.org/resource/Feedly"},"p":{"type":"uri","value":"http://dbpedia.org/property/license"},"o":{"type":"uri","value":"http://dbpedia.org/resource/Freemium"}},{"s":{"type":"uri","value":"http://dbpedia.org/resource/Feedly"},"p":{"type":"uri","value":"http://purl.org/dc/terms/subject"},"o":{"type":"uri","value":"http://dbpedia.org/resource/Category:IOS_software"}},{"s":{"type":"uri","value":"http://dbpedia.org/resource/Feedly"},"p":{"type":"uri","value":"http://www.w3.org/2002/07/owl#sameAs"},"o":{"type":"uri","value":"http://yago-knowledge.org/resource/Feedly"}},{"s":{"type":"uri","value":"http://dbpedia.org/resource/Feedly"},"p":{"type":"uri","value":"http://dbpedia.org/ontology/abstract"},"o":{"type":"literal","value":"Feedly是一个RSS聚合器应用程序，支持各种网页浏览器和运行iOS或Android的移动设备，也是一个基于云端的服务。其从各种在线资源聚合用户自定的新闻订阅源，并可与他人分享。Feedly由DevHD于2008年推出。","lang":"zh"}},{"s":{"type":"uri","value":"http://dbpedia.org/resource/Feedly"},"p":{"type":"uri","value":"http://www.w3.org/1999/02/22-rdf-syntax-ns#type"},"o":{"type":"uri","value":"http://dbpedia.org/class/yago/CodingSystem106353757"}},{"s":{"type":"uri","value":"http://dbpedia.org/resource/Feedly.com"},"p":{"type":"uri","value":"http://dbpedia.org/ontology/wikiPageRedirects"},"o":{"type":"uri","value":"http://dbpedia.org/resource/Feedly"}},{"s":{"type":"uri","value":"http://dbpedia.org/resource/Feedly"},"p":{"type":"uri","value":"http://www.w3.org/1999/02/22-rdf-syntax-ns#type"},"o":{"type":"uri","value":"http://dbpedia.org/class/yago/WrittenCommunication106349220"}},{"s":{"type":"uri","value":"http://dbpedia.org/resource/Feedly"},"p":{"type":"uri","value":"http://www.w3.org/ns/prov#wasDerivedFrom"},"o":{"type":"uri","value":"http://en.wikipedia.org/wiki/Feedly?oldid=692975886"}},{"s":{"type":"uri","value":"http://dbpedia.org/resource/Feedly"},"p":{"type":"uri","value":"http://dbpedia.org/ontology/abstract"},"o":{"type":"literal","value":"Feedly is a news aggregator application for various web browsers and mobile devices running iOS and Android, also available as a cloud-based service. It compiles news feeds from a variety of online sources for the user to customize and share with others. Feedly was first released by DevHD in 2008.","lang":"en"}},{"s":{"type":"uri","value":"http://dbpedia.org/resource/Feedly"},"p":{"type":"uri","value":"http://dbpedia.org/ontology/programmingLanguage"},"o":{"type":"uri","value":"http://dbpedia.org/resource/Cascading_Style_Sheets"}},{"s":{"type":"uri","value":"http://dbpedia.org/resource/Feedly"},"p":{"type":"uri","value":"http://purl.org/dc/terms/subject"},"o":{"type":"uri","value":"http://dbpedia.org/resource/Category:Web_software"}},{"s":{"type":"uri","value":"http://dbpedia.org/resource/Feedly"},"p":{"type":"uri","value":"http://www.w3.org/2000/01/rdf-schema#label"},"o":{"type":"literal","value":"Feedly","lang":"ja"}},{"s":{"type":"uri","value":"http://dbpedia.org/resource/Feedly"},"p":{"type":"uri","value":"http://dbpedia.org/ontology/license"},"o":{"type":"uri","value":"http://dbpedia.org/resource/Freemium"}},{"s":{"type":"uri","value":"http://dbpedia.org/resource/Feedly"},"p":{"type":"uri","value":"http://www.w3.org/2000/01/rdf-schema#comment"},"o":{"type":"literal","value":"Feedly is een feedreader voor RSS- en Atom-feeds. Het programma is beschikbaar als webversie en als app voor Android en iOS. Daarnaast bestaan er browserextensies voor Mozilla Firefox, Google Chrome, Safari en Opera.Feedly berustte oorspronkelijk op de technologie van Google Reader. Met de stopzetting van Google Reader op 1 juli 2013 werd er echter enkele weken voorheen overgeschakeld naar een eigen backend. Feedly biedt een vormgeving die meer bij een digitale krant aanleunt. Er kan ingelogd worden met onder andere een Google-, Facebook- of Twitteraccount.","lang":"nl"}},{"s":{"type":"uri","value":"http://dbpedia.org/resource/Feedly"},"p":{"type":"uri","value":"http://www.w3.org/1999/02/22-rdf-syntax-ns#type"},"o":{"type":"uri","value":"http://dbpedia.org/class/yago/Writing106359877"}},{"s":{"type":"uri","value":"http://dbpedia.org/resource/Feedly"},"p":{"type":"uri","value":"http://www.w3.org/1999/02/22-rdf-syntax-ns#type"},"o":{"type":"uri","value":"http://dbpedia.org/class/yago/Software106566077"}},{"s":{"type":"uri","value":"http://dbpedia.org/resource/Feedly"},"p":{"type":"uri","value":"http://www.w3.org/1999/02/22-rdf-syntax-ns#type"},"o":{"type":"uri","value":"http://www.wikidata.org/entity/Q7397"}},{"s":{"type":"uri","value":"http://dbpedia.org/resource/Feedly"},"p":{"type":"uri","value":"http://dbpedia.org/ontology/abstract"},"o":{"type":"literal","value":"Feedly è un aggregatore di notizie disponibile attraverso piattaforma web consultabile con browser web e applicazioni per dispositivi iOS e Android. Valide applicazioni di terze parti che sfruttano il servizio sono disponibili per telefoni Windows ed altri sistemi operativi (qui l'elenco completo: ). Questo strumento rende disponibile la lettura di flussi (feed) di notizie dalle fonti che interessano l'utente, affiancando all'inserimento di fonti personalizzate categorie consigliate. Si tratta di un'esperienza gratuita arricchita di funzionalità avanzate a pagamento. Feedly è stato distribuito per la prima volta da DevHD nel 2008.","lang":"it"}},{"s":{"type":"uri","value":"http://dbpedia.org/resource/Feedly"},"p":{"type":"uri","value":"http://www.w3.org/1999/02/22-rdf-syntax-ns#type"},"o":{"type":"uri","value":"http://dbpedia.org/ontology/Software"}},{"s":{"type":"uri","value":"http://dbpedia.org/resource/Feedly"},"p":{"type":"uri","value":"http://dbpedia.org/ontology/genre"},"o":{"type":"uri","value":"http://dbpedia.org/resource/News_aggregator"}},{"s":{"type":"uri","value":"http://dbpedia.org/resource/Feedly"},"p":{"type":"uri","value":"http://www.w3.org/2002/07/owl#sameAs"},"o":{"type":"uri","value":"http://ja.dbpedia.org/resource/Feedly"}},{"s":{"type":"uri","value":"http://dbpedia.org/resource/Feedly"},"p":{"type":"uri","value":"http://dbpedia.org/property/platform"},"o":{"type":"uri","value":"http://dbpedia.org/resource/Web_browser"}},{"s":{"type":"uri","value":"http://dbpedia.org/resource/Feedly"},"p":{"type":"uri","value":"http://www.w3.org/2000/01/rdf-schema#label"},"o":{"type":"literal","value":"Feedly","lang":"nl"}},{"s":{"type":"uri","value":"http://dbpedia.org/resource/Feedly"},"p":{"type":"uri","value":"http://www.w3.org/2002/07/owl#sameAs"},"o":{"type":"uri","value":"http://es.dbpedia.org/resource/Feedly"}},{"s":{"type":"uri","value":"http://dbpedia.org/resource/Feedly"},"p":{"type":"uri","value":"http://dbpedia.org/ontology/computingPlatform"},"o":{"type":"uri","value":"http://dbpedia.org/resource/Mobile_device"}},{"s":{"type":"uri","value":"http://dbpedia.org/resource/Feedly"},"p":{"type":"uri","value":"http://www.w3.org/2000/01/rdf-schema#comment"},"o":{"type":"literal","value":"Feedly est un agrégateur de flux RSS et Atom en ligne. Il est accessible par un navigateur internet, et est également disponible sous forme d'application pour smartphone. Il permet, via une interface web ou une application mobile, de gérer et personnaliser ses abonnements à des flux RSS.L'application web, développée par la société informatique DevHD, est sortie le . Le , à la suite de l'annonce de fermeture de Google Reader, Feedly annonce 500 000 nouveaux utilisateurs en 48 heures. Entre avril et , le nombre d'utilisateurs total passe de 3 à 12 millions.","lang":"fr"}},{"s":{"type":"uri","value":"http://dbpedia.org/resource/Feedly"},"p":{"type":"uri","value":"http://www.w3.org/2000/01/rdf-schema#comment"},"o":{"type":"literal","value":"FeedlyとはいくつかウェブブラウザやiOSとAndroidの携帯端末に対応しているニュースアグリゲータアプリケーションである。インターネット上の数あるウェブサイトのニュースフィードを収集し他人と共有することができる。2008年に初版がDevHDによって公開された。","lang":"ja"}},{"s":{"type":"uri","value":"http://dbpedia.org/resource/Feedly"},"p":{"type":"uri","value":"http://dbpedia.org/ontology/abstract"},"o":{"type":"literal","value":"Feedly — новостной агрегатор, представленный как альтернатива закрывшемуся Google Reader.","lang":"ru"}},{"s":{"type":"uri","value":"http://dbpedia.org/resource/Feedly"},"p":{"type":"uri","value":"http://www.w3.org/1999/02/22-rdf-syntax-ns#type"},"o":{"type":"uri","value":"http://dbpedia.org/ontology/Work"}},{"s":{"type":"uri","value":"http://dbpedia.org/resource/Feedly"},"p":{"type":"uri","value":"http://www.w3.org/2002/07/owl#sameAs"},"o":{"type":"uri","value":"http://wikidata.dbpedia.org/resource/Q5441251"}},{"s":{"type":"uri","value":"http://dbpedia.org/resource/Feedly"},"p":{"type":"uri","value":"http://dbpedia.org/ontology/wikiPageID"},"o":{"type":"literal","value":34740185,"datatype":"http://www.w3.org/2001/XMLSchema#integer"}},{"s":{"type":"uri","value":"http://dbpedia.org/resource/Feedly"},"p":{"type":"uri","value":"http://xmlns.com/foaf/0.1/name"},"o":{"type":"literal","value":"Feedly","lang":"en"}},{"s":{"type":"uri","value":"http://dbpedia.org/resource/Feedly"},"p":{"type":"uri","value":"http://dbpedia.org/ontology/abstract"},"o":{"type":"literal","value":"Feedly es un lector de RSS que permite organizar y acceder rápidamente desde un navegador web o de sus aplicaciones para teléfonos inteligentes a todas las noticias y actualizaciones de blogs y demás páginas que el sistema soporta. Entre otras características permite ordenar todos los contenidos de manera que facilita al usuario ahorrar tiempo por no tener que revisar una a una todas las fuentes de noticias.","lang":"es"}},{"s":{"type":"uri","value":"http://dbpedia.org/resource/Feedly"},"p":{"type":"uri","value":"http://xmlns.com/foaf/0.1/isPrimaryTopicOf"},"o":{"type":"uri","value":"http://en.wikipedia.org/wiki/Feedly"}},{"s":{"type":"uri","value":"http://dbpedia.org/resource/Feedly"},"p":{"type":"uri","value":"http://dbpedia.org/property/genre"},"o":{"type":"uri","value":"http://dbpedia.org/resource/News_aggregator"}},{"s":{"type":"uri","value":"http://dbpedia.org/resource/Feedly"},"p":{"type":"uri","value":"http://www.w3.org/1999/02/22-rdf-syntax-ns#type"},"o":{"type":"uri","value":"http://schema.org/CreativeWork"}},{"s":{"type":"uri","value":"http://dbpedia.org/resource/Feedly"},"p":{"type":"uri","value":"http://dbpedia.org/ontology/computingPlatform"},"o":{"type":"uri","value":"http://dbpedia.org/resource/Web_browser"}},{"s":{"type":"uri","value":"http://dbpedia.org/resource/Feedly"},"p":{"type":"uri","value":"http://dbpedia.org/property/programmingLanguage"},"o":{"type":"uri","value":"http://dbpedia.org/resource/HTML"}},{"s":{"type":"uri","value":"http://en.wikipedia.org/wiki/Feedly"},"p":{"type":"uri","value":"http://xmlns.com/foaf/0.1/primaryTopic"},"o":{"type":"uri","value":"http://dbpedia.org/resource/Feedly"}},{"s":{"type":"uri","value":"http://dbpedia.org/resource/Feedly"},"p":{"type":"uri","value":"http://www.w3.org/2000/01/rdf-schema#comment"},"o":{"type":"literal","value":"Feedly es un lector de RSS que permite organizar y acceder rápidamente desde un navegador web o de sus aplicaciones para teléfonos inteligentes a todas las noticias y actualizaciones de blogs y demás páginas que el sistema soporta.Entre otras características permite ordenar todos los contenidos de manera que facilita al usuario ahorrar tiempo por no tener que revisar una a una todas las fuentes de noticias.","lang":"es"}},{"s":{"type":"uri","value":"http://dbpedia.org/resource/Feedly"},"p":{"type":"uri","value":"http://www.w3.org/1999/02/22-rdf-syntax-ns#type"},"o":{"type":"uri","value":"http://www.w3.org/2002/07/owl#Thing"}},{"s":{"type":"uri","value":"http://dbpedia.org/resource/Feedly"},"p":{"type":"uri","value":"http://www.w3.org/2000/01/rdf-schema#comment"},"o":{"type":"literal","value":"Feedly è un aggregatore di notizie disponibile attraverso piattaforma web consultabile con browser web e applicazioni per dispositivi iOS e Android. Valide applicazioni di terze parti che sfruttano il servizio sono disponibili per telefoni Windows ed altri sistemi operativi (qui l'elenco completo: ). Questo strumento rende disponibile la lettura di flussi (feed) di notizie dalle fonti che interessano l'utente, affiancando all'inserimento di fonti personalizzate categorie consigliate. Si tratta di un'esperienza gratuita arricchita di funzionalità avanzate a pagamento. Feedly è stato distribuito per la prima volta da DevHD nel 2008.","lang":"it"}},{"s":{"type":"uri","value":"http://dbpedia.org/resource/Feedly"},"p":{"type":"uri","value":"http://www.w3.org/2000/01/rdf-schema#label"},"o":{"type":"literal","value":"Feedly","lang":"es"}},{"s":{"type":"uri","value":"http://dbpedia.org/resource/Feedly"},"p":{"type":"uri","value":"http://dbpedia.org/ontology/abstract"},"o":{"type":"literal","value":"Feedly is een feedreader voor RSS- en Atom-feeds. Het programma is beschikbaar als webversie en als app voor Android en iOS. Daarnaast bestaan er browserextensies voor Mozilla Firefox, Google Chrome, Safari en Opera. Feedly berustte oorspronkelijk op de technologie van Google Reader. Met de stopzetting van Google Reader op 1 juli 2013 werd er echter enkele weken voorheen overgeschakeld naar een eigen backend. Feedly biedt een vormgeving die meer bij een digitale krant aanleunt. Er kan ingelogd worden met onder andere een Google-, Facebook- of Twitteraccount.","lang":"nl"}},{"s":{"type":"uri","value":"http://dbpedia.org/resource/Feedly"},"p":{"type":"uri","value":"http://www.w3.org/2002/07/owl#sameAs"},"o":{"type":"uri","value":"http://it.dbpedia.org/resource/Feedly"}},{"s":{"type":"uri","value":"http://dbpedia.org/resource/Feedly"},"p":{"type":"uri","value":"http://dbpedia.org/property/programmingLanguage"},"o":{"type":"uri","value":"http://dbpedia.org/resource/JavaScript"}},{"s":{"type":"uri","value":"http://dbpedia.org/resource/Feedly"},"p":{"type":"uri","value":"http://www.w3.org/2002/07/owl#sameAs"},"o":{"type":"uri","value":"http://www.wikidata.org/entity/Q5441251"}},{"s":{"type":"uri","value":"http://dbpedia.org/resource/Feedly"},"p":{"type":"uri","value":"http://www.w3.org/1999/02/22-rdf-syntax-ns#type"},"o":{"type":"uri","value":"http://dbpedia.org/class/yago/Abstraction100002137"}},{"s":{"type":"uri","value":"http://dbpedia.org/resource/Feedly"},"p":{"type":"uri","value":"http://dbpedia.org/ontology/programmingLanguage"},"o":{"type":"uri","value":"http://dbpedia.org/resource/Java_(programming_language)"}},{"s":{"type":"uri","value":"http://dbpedia.org/resource/Feedly"},"p":{"type":"uri","value":"http://dbpedia.org/property/programmingLanguage"},"o":{"type":"uri","value":"http://dbpedia.org/resource/Java_(programming_language)"}},{"s":{"type":"uri","value":"http://dbpedia.org/resource/Feedly"},"p":{"type":"uri","value":"http://dbpedia.org/ontology/programmingLanguage"},"o":{"type":"uri","value":"http://dbpedia.org/resource/JavaScript"}},{"s":{"type":"uri","value":"http://dbpedia.org/resource/Feedly"},"p":{"type":"uri","value":"http://www.w3.org/2000/01/rdf-schema#label"},"o":{"type":"literal","value":"Feedly","lang":"it"}},{"s":{"type":"uri","value":"http://dbpedia.org/resource/Feedly"},"p":{"type":"uri","value":"http://dbpedia.org/ontology/abstract"},"o":{"type":"literal","value":"FeedlyとはいくつかウェブブラウザやiOSとAndroidの携帯端末に対応しているニュースアグリゲータアプリケーションである。インターネット上の数あるウェブサイトのニュースフィードを収集し他人と共有することができる。2008年に初版がDevHDによって公開された。","lang":"ja"}},{"s":{"type":"uri","value":"http://dbpedia.org/resource/Feedly"},"p":{"type":"uri","value":"http://www.w3.org/2000/01/rdf-schema#label"},"o":{"type":"literal","value":"Feedly","lang":"fr"}},{"s":{"type":"uri","value":"http://dbpedia.org/resource/Feedly"},"p":{"type":"uri","value":"http://dbpedia.org/property/platform"},"o":{"type":"uri","value":"http://dbpedia.org/resource/Mobile_device"}},{"s":{"type":"uri","value":"http://dbpedia.org/resource/Feedly"},"p":{"type":"uri","value":"http://www.w3.org/2002/07/owl#sameAs"},"o":{"type":"uri","value":"http://fr.dbpedia.org/resource/Feedly"}},{"s":{"type":"uri","value":"http://dbpedia.org/resource/Feedly"},"p":{"type":"uri","value":"http://www.w3.org/2000/01/rdf-schema#comment"},"o":{"type":"literal","value":"Feedly is a news aggregator application for various web browsers and mobile devices running iOS and Android, also available as a cloud-based service. It compiles news feeds from a variety of online sources for the user to customize and share with others. Feedly was first released by DevHD in 2008.","lang":"en"}},{"s":{"type":"uri","value":"http://dbpedia.org/resource/Feedly"},"p":{"type":"uri","value":"http://www.w3.org/1999/02/22-rdf-syntax-ns#type"},"o":{"type":"uri","value":"http://www.wikidata.org/entity/Q386724"}},{"s":{"type":"uri","value":"http://dbpedia.org/resource/Feedly"},"p":{"type":"uri","value":"http://dbpedia.org/ontology/programmingLanguage"},"o":{"type":"uri","value":"http://dbpedia.org/resource/HTML"}},{"s":{"type":"uri","value":"http://dbpedia.org/resource/Feedly"},"p":{"type":"uri","value":"http://xmlns.com/foaf/0.1/homepage"},"o":{"type":"uri","value":"https://feedly.com"}},{"s":{"type":"uri","value":"http://dbpedia.org/resource/Feedly"},"p":{"type":"uri","value":"http://dbpedia.org/ontology/abstract"},"o":{"type":"literal","value":"Feedly est un agrégateur de flux RSS et Atom en ligne. Il est accessible par un navigateur internet, et est également disponible sous forme d'application pour smartphone. Il permet, via une interface web ou une application mobile, de gérer et personnaliser ses abonnements à des flux RSS. L'application web, développée par la société informatique DevHD, est sortie le . Le , à la suite de l'annonce de fermeture de Google Reader, Feedly annonce 500 000 nouveaux utilisateurs en 48 heures. Entre avril et , le nombre d'utilisateurs total passe de 3 à 12 millions.","lang":"fr"}},{"s":{"type":"uri","value":"http://dbpedia.org/resource/Feedly"},"p":{"type":"uri","value":"http://www.w3.org/2000/01/rdf-schema#label"},"o":{"type":"literal","value":"Feedly","lang":"ru"}},{"s":{"type":"uri","value":"http://dbpedia.org/resource/Feedly"},"p":{"type":"uri","value":"http://dbpedia.org/ontology/wikiPageRevisionID"},"o":{"type":"literal","value":692975886,"datatype":"http://www.w3.org/2001/XMLSchema#integer"}},{"s":{"type":"uri","value":"http://dbpedia.org/resource/Feedly"},"p":{"type":"uri","value":"http://www.w3.org/1999/02/22-rdf-syntax-ns#type"},"o":{"type":"uri","value":"http://dbpedia.org/class/yago/Code106355894"}},{"s":{"type":"uri","value":"http://dbpedia.org/resource/Feedly"},"p":{"type":"uri","value":"http://www.w3.org/2000/01/rdf-schema#label"},"o":{"type":"literal","value":"Feedly","lang":"en"}},{"s":{"type":"uri","value":"http://dbpedia.org/resource/Feedly"},"p":{"type":"uri","value":"http://purl.org/dc/terms/subject"},"o":{"type":"uri","value":"http://dbpedia.org/resource/Category:Android_(operating_system)_software"}},{"s":{"type":"uri","value":"http://dbpedia.org/resource/Feedly"},"p":{"type":"uri","value":"http://dbpedia.org/property/name"},"o":{"type":"literal","value":"Feedly","lang":"en"}},{"s":{"type":"uri","value":"http://dbpedia.org/resource/Feedly"},"p":{"type":"uri","value":"http://www.w3.org/2000/01/rdf-schema#label"},"o":{"type":"literal","value":"Feedly","lang":"zh"}},{"s":{"type":"uri","value":"http://dbpedia.org/resource/Feedly"},"p":{"type":"uri","value":"http://dbpedia.org/property/programmingLanguage"},"o":{"type":"uri","value":"http://dbpedia.org/resource/Cascading_Style_Sheets"}},{"s":{"type":"uri","value":"http://dbpedia.org/resource/Feedly"},"p":{"type":"uri","value":"http://www.w3.org/1999/02/22-rdf-syntax-ns#type"},"o":{"type":"uri","value":"http://dbpedia.org/class/yago/Communication100033020"}},{"s":{"type":"uri","value":"http://dbpedia.org/resource/Feedly"},"p":{"type":"uri","value":"http://dbpedia.org/ontology/wikiPageExternalLink"},"o":{"type":"uri","value":"https://feedly.com"}}]}}